LICENSE
MANIFEST.in
README.md
setup.py
quickQrLib/__init__.py
quickQrLib.egg-info/PKG-INFO
quickQrLib.egg-info/SOURCES.txt
quickQrLib.egg-info/dependency_links.txt
quickQrLib.egg-info/requires.txt
quickQrLib.egg-info/top_level.txt
quickQrLib/_test_util/__init__.py
quickQrLib/_test_util/test.py
quickQrLib/jwt_util/__init__.py
quickQrLib/jwt_util/jwt_utils.py
quickQrLib/method_decorators/__init__.py
quickQrLib/method_decorators/timer.py
quickQrLib/middleware_util/__init__.py
quickQrLib/middleware_util/csp_middleware.py
quickQrLib/middleware_util/prometheus_middleware.py
quickQrLib/middleware_util/refresh_token_middleware.py
quickQrLib/middleware_util/token_utils.py
quickQrLib/permissions_util/__init__.py
quickQrLib/permissions_util/permissions_utils.py
quickQrLib/pgcrypto_util/__init__.py
quickQrLib/pgcrypto_util/database_encryption.py
quickQrLib/qr_encryption_util/__init__.py
quickQrLib/qr_encryption_util/aes_key.pem
quickQrLib/qr_encryption_util/encrypt_aes.py
quickQrLib/redis_utils/__init__.py
quickQrLib/redis_utils/handshake_check.py
quickQrLib/redis_utils/redis_helper.py
quickQrLib/s3_util/__init__.py
quickQrLib/s3_util/s3_storage_util.py
quickQrLib/signature_util/__init__.py
quickQrLib/signature_util/public_key.pem
quickQrLib/signature_util/signatures.py
quickQrLib/time_util/__init__.py
quickQrLib/time_util/date_time_helpers.py