Metadata-Version: 2.1
Name: quickQrLib
Version: 2.0.68
License-File: LICENSE
Requires-Dist: djangorestframework-simplejwt
Requires-Dist: django
Requires-Dist: djangorestframework
Requires-Dist: cryptography
Requires-Dist: boto3
Requires-Dist: python-dateutil
Requires-Dist: pytz
Requires-Dist: requests
Requires-Dist: redis
Requires-Dist: django-environ
Requires-Dist: pycryptodome
Requires-Dist: prometheus_client
